{
  "Time": "2025-12-13T06:41:14.5747574Z",
  "Players": [
    {
      "Name": "nixware enjoyer",
      "Steam": "76561198767127370",
      "Score": 3,
      "Time": "07:53"
    },
    {
      "Name": "han",
      "Steam": "76561198983792841",
      "Score": 4,
      "Time": "23:56"
    },
    {
      "Name": "-",
      "Steam": "76561198774315242",
      "Score": 45,
      "Time": "??:??"
    },
    {
      "Name": "Arthur",
      "Steam": "76561198772884947",
      "Score": 14,
      "Time": "05:47"
    },
    {
      "Name": "BEST \uD83D\uDE01",
      "Steam": "76561198786904680",
      "Score": 46,
      "Time": "??:??"
    },
    {
      "Name": "1",
      "Steam": "76561199819844991",
      "Score": 5,
      "Time": "??:??"
    }
  ]
}