{
  "Time": "2026-03-27T12:24:40.76719Z",
  "Players": [
    {
      "Name": "zyro",
      "Steam": "76561198740186999",
      "Score": 94,
      "Time": "??:??"
    },
    {
      "Name": "thatguy",
      "Steam": "76561198335255015",
      "Score": 20,
      "Time": "38:48"
    },
    {
      "Name": "n1cknz?",
      "Steam": "76561198760723734",
      "Score": 32,
      "Time": "19:54"
    },
    {
      "Name": "Xeil",
      "Steam": "76561199834620426",
      "Score": 0,
      "Time": "05:41"
    },
    {
      "Name": "tw1stie⚡",
      "Steam": "76561199188655006",
      "Score": 4,
      "Time": "33:08"
    },
    {
      "Name": "K03",
      "Steam": "76561199788609972",
      "Score": 25,
      "Time": "28:01"
    }
  ]
}