{
  "Time": "2026-03-22T11:24:31.4289927Z",
  "Players": [
    {
      "Name": "> AURA | unfriendly gaten",
      "Steam": "76561198791732336",
      "Score": 27,
      "Time": "81:20"
    },
    {
      "Name": "n1cknz?",
      "Steam": "76561198760723734",
      "Score": 19,
      "Time": "26:40"
    },
    {
      "Name": "zyro",
      "Steam": "76561198740186999",
      "Score": 29,
      "Time": "328:39"
    },
    {
      "Name": "91",
      "Steam": "76561199303359682",
      "Score": 25,
      "Time": "11:33"
    },
    {
      "Name": "esther luv tea",
      "Steam": "76561198124032291",
      "Score": 0,
      "Time": "84:21"
    },
    {
      "Name": "noname",
      "Steam": "76561198800250172",
      "Score": 39,
      "Time": "22:58"
    },
    {
      "Name": "Свиня爱",
      "Steam": "76561199410471185",
      "Score": 0,
      "Time": "78:40"
    },
    {
      "Name": "$$$$$$$",
      "Steam": "76561199229682369",
      "Score": 27,
      "Time": "46:33"
    },
    {
      "Name": "kryozzz",
      "Steam": "76561199485394741",
      "Score": 4,
      "Time": "??:??"
    },
    {
      "Name": "MTCB",
      "Steam": "76561199172297938",
      "Score": 0,
      "Time": "25:35"
    }
  ]
}