{
  "Time": "2026-01-09T16:50:31.5809679Z",
  "Players": [
    {
      "Name": "Alt is Supaman",
      "Steam": "76561199834727236",
      "Score": 34,
      "Time": "64:13"
    },
    {
      "Name": "`A",
      "Steam": "76561199699289339",
      "Score": 2,
      "Time": "06:36"
    },
    {
      "Name": "plgmisses",
      "Steam": "76561199717612677",
      "Score": 35,
      "Time": "32:29"
    },
    {
      "Name": "Ping Pong",
      "Steam": "76561198782416061",
      "Score": 17,
      "Time": "32:11"
    },
    {
      "Name": "thatguy",
      "Steam": "76561198335255015",
      "Score": 2,
      "Time": "04:08"
    },
    {
      "Name": "1",
      "Steam": "76561198759796859",
      "Score": 32,
      "Time": "24:12"
    },
    {
      "Name": "AIMWARE",
      "Steam": "76561199303359682",
      "Score": 9,
      "Time": "38:42"
    }
  ]
}