{
  "Time": "2025-11-07T23:23:21.7342868Z",
  "Players": [
    {
      "Name": "blahx909",
      "Steam": "76561198775054336",
      "Score": 23,
      "Time": "12:27"
    },
    {
      "Name": "Bhg",
      "Steam": "76561199647822907",
      "Score": 0,
      "Time": "??:??"
    },
    {
      "Name": "Jiso_99",
      "Steam": "76561199525310443",
      "Score": 33,
      "Time": "??:??"
    },
    {
      "Name": "kicken",
      "Steam": "76561199370092055",
      "Score": 32,
      "Time": "??:??"
    },
    {
      "Name": "私は黒人が嫌いだ",
      "Steam": "76561199680240727",
      "Score": 16,
      "Time": "??:??"
    }
  ]
}