{
  "Time": "2026-01-18T02:02:20.0328147Z",
  "Players": [
    {
      "Name": "vlone custom model",
      "Steam": "76561199678608838",
      "Score": 8,
      "Time": "2026-01-18T02:02:20.0328147Z"
    },
    {
      "Name": "trenbolonacetate",
      "Steam": "76561198790879092",
      "Score": 4,
      "Time": "2026-01-18T02:02:20.0328147Z"
    },
    {
      "Name": "virginiasok1966",
      "Steam": "76561199847918857",
      "Score": 0,
      "Time": "2026-01-18T02:02:20.0328147Z"
    },
    {
      "Name": "James",
      "Steam": "76561199121215178",
      "Score": 2,
      "Time": "2026-01-18T02:02:20.0328147Z"
    }
  ]
}