{
  "Time": "2025-11-20T17:36:05.4727738Z",
  "Players": [
    {
      "Name": "Mrow",
      "Steam": "76561199402054529",
      "Score": 4,
      "Time": "29:52"
    },
    {
      "Name": "?",
      "Steam": "76561199811991561",
      "Score": 2,
      "Time": "14:22"
    },
    {
      "Name": "ᶜᵒᵘᵍᵃʳᴸᵒᵛᵉʳ",
      "Steam": "76561199881476055",
      "Score": 0,
      "Time": "25:10"
    },
    {
      "Name": "bite  trip",
      "Steam": "76561198428564314",
      "Score": 0,
      "Time": "09:07"
    }
  ]
}