{
  "Time": "2025-12-02T20:00:49.8618349Z",
  "Players": [
    {
      "Name": "superstar >:3",
      "Steam": "76561198768490015",
      "Score": 35,
      "Time": "??:??"
    },
    {
      "Name": "astro",
      "Steam": "76561198782333753",
      "Score": 30,
      "Time": "165:43"
    },
    {
      "Name": "Mr Pineapple",
      "Steam": "76561199126066907",
      "Score": 24,
      "Time": "22:22"
    },
    {
      "Name": "SuckMyBump",
      "Steam": "76561199473656862",
      "Score": 12,
      "Time": "??:??"
    },
    {
      "Name": "Faded",
      "Steam": "76561198762584651",
      "Score": 31,
      "Time": "??:??"
    },
    {
      "Name": "cloxid",
      "Steam": "76561198166519466",
      "Score": 30,
      "Time": "01:07"
    },
    {
      "Name": "Zaxh",
      "Steam": "76561198366421077",
      "Score": 9,
      "Time": "??:??"
    }
  ]
}