{
  "Time": "2026-01-06T14:38:26.0648301Z",
  "Players": [
    {
      "Name": "\uD835\uDCFB\uD835\uDCEA\uD835\uDCFE\uD835\uDCF5\uD835\uDCFB\uD835\uDCEE\uD835\uDCF0\uD835\uDCEE",
      "Steam": "76561199782010194",
      "Score": 54,
      "Time": "2026-01-06T14:38:26.0648301Z"
    },
    {
      "Name": "nixware.cc/блямисснул",
      "Steam": "76561198950053715",
      "Score": 0,
      "Time": "2026-01-06T14:38:26.0648301Z"
    },
    {
      "Name": "Вафля",
      "Steam": "76561198780597741",
      "Score": 4,
      "Time": "2026-01-06T14:38:26.0648301Z"
    },
    {
      "Name": "✪ ⓊrSaⒸhE ✪",
      "Steam": "76561198766752101",
      "Score": 16,
      "Time": "2026-01-06T14:38:26.0648301Z"
    },
    {
      "Name": "makkann",
      "Steam": "76561199470112975",
      "Score": 2,
      "Time": "2026-01-06T14:38:26.0648301Z"
    },
    {
      "Name": ">w<",
      "Steam": "76561198281724910",
      "Score": 5,
      "Time": "2026-01-06T14:38:26.0648301Z"
    }
  ]
}