{
  "Time": "2026-03-15T15:10:53.9212864Z",
  "Players": [
    {
      "Name": "\"'",
      "Steam": "76561199028888055",
      "Score": 0,
      "Time": "??:??"
    },
    {
      "Name": ">.<",
      "Steam": "76561199042138318",
      "Score": 2,
      "Time": "??:??"
    },
    {
      "Name": "Grizly",
      "Steam": "76561198188465877",
      "Score": 16,
      "Time": "??:??"
    },
    {
      "Name": "Jugga™ #Give Skeet Invite!",
      "Steam": "76561199538446621",
      "Score": 0,
      "Time": "00:47"
    },
    {
      "Name": "trebor",
      "Steam": "76561199805752338",
      "Score": 0,
      "Time": "??:??"
    },
    {
      "Name": "EasyAF",
      "Steam": "76561198417239008",
      "Score": 14,
      "Time": "12:22"
    },
    {
      "Name": "ÖÄ",
      "Steam": "76561198885533250",
      "Score": 4,
      "Time": "??:??"
    },
    {
      "Name": "pxnch",
      "Steam": "76561198827507307",
      "Score": 8,
      "Time": "??:??"
    },
    {
      "Name": "70ee3618de83.tmp",
      "Steam": "76561198731352731",
      "Score": 2,
      "Time": "??:??"
    },
    {
      "Name": "angel",
      "Steam": "76561199798812373",
      "Score": 18,
      "Time": "40:59"
    },
    {
      "Name": "Real Shit",
      "Steam": "76561199525508650",
      "Score": 2,
      "Time": "??:??"
    },
    {
      "Name": "catsssssss",
      "Steam": "76561198794467793",
      "Score": 6,
      "Time": "11:12"
    },
    {
      "Name": "jAMAL",
      "Steam": "76561198963830393",
      "Score": 6,
      "Time": "11:47"
    }
  ]
}