{
  "Time": "2025-11-07T22:31:39.6271696Z",
  "Players": [
    {
      "Name": "✪ nepS",
      "Steam": "76561199407070160",
      "Score": 24,
      "Time": "??:??"
    },
    {
      "Name": "volvo enjoyer",
      "Steam": "76561199883686960",
      "Score": 11,
      "Time": "??:??"
    },
    {
      "Name": "rcx",
      "Steam": "76561199784226010",
      "Score": 21,
      "Time": "18:10"
    },
    {
      "Name": "bbbbbbbbbb",
      "Steam": "76561198779174796",
      "Score": 45,
      "Time": "27:26"
    },
    {
      "Name": "BoB",
      "Steam": "76561199095425240",
      "Score": 0,
      "Time": "??:??"
    },
    {
      "Name": "astra nanosense on top",
      "Steam": "76561199407469923",
      "Score": 0,
      "Time": "08:46"
    },
    {
      "Name": "Neo",
      "Steam": "76561199201440406",
      "Score": 0,
      "Time": "34:25"
    }
  ]
}