{
  "Time": "2025-11-12T18:06:18.5615426Z",
  "Players": [
    {
      "Name": "femnig",
      "Steam": "76561199512917213",
      "Score": 39,
      "Time": "2025-11-12T18:06:18.5615426Z"
    },
    {
      "Name": "evilmane лашок",
      "Steam": "76561198786921336",
      "Score": 0,
      "Time": "2025-11-12T18:06:18.5615426Z"
    },
    {
      "Name": "bomboclat",
      "Steam": "76561199877819718",
      "Score": 0,
      "Time": "2025-11-12T18:06:18.5615426Z"
    },
    {
      "Name": ".",
      "Steam": "76561199667054562",
      "Score": 39,
      "Time": "2025-11-12T18:06:18.5615426Z"
    },
    {
      "Name": "Reyna Main<3",
      "Steam": "76561199812145400",
      "Score": 39,
      "Time": "2025-11-12T18:06:18.5615426Z"
    },
    {
      "Name": "Feet Enjoyer",
      "Steam": "76561199828015418",
      "Score": 69,
      "Time": "2025-11-12T18:06:18.5615426Z"
    },
    {
      "Name": "MISSED",
      "Steam": "76561198839239352",
      "Score": 0,
      "Time": "2025-11-12T18:06:18.5615426Z"
    }
  ]
}