{
  "Time": "2026-02-02T01:02:29.9432681Z",
  "Players": [
    {
      "Name": "ozempeek",
      "Steam": "76561199241125970",
      "Score": 4,
      "Time": "69:19"
    },
    {
      "Name": "イシラ",
      "Steam": "76561198764706139",
      "Score": 0,
      "Time": "11:42"
    },
    {
      "Name": "TRPLBABY",
      "Steam": "76561198413331142",
      "Score": 8,
      "Time": "11:31"
    },
    {
      "Name": "Penelope",
      "Steam": "76561198215570155",
      "Score": 12,
      "Time": "??:??"
    },
    {
      "Name": "Mjay",
      "Steam": "76561199237707727",
      "Score": 3,
      "Time": "??:??"
    },
    {
      "Name": "Grajchłopiec Kasti",
      "Steam": "76561199833286399",
      "Score": 12,
      "Time": "34:37"
    },
    {
      "Name": "ZwMapViewOfSection",
      "Steam": "76561199884966036",
      "Score": 5,
      "Time": "??:??"
    }
  ]
}