{
  "Time": "2025-11-15T09:18:20.7570285Z",
  "Players": [
    {
      "Name": "\"'",
      "Steam": "76561199028888055",
      "Score": 0,
      "Time": "??:??"
    },
    {
      "Name": "alterex24",
      "Steam": "76561198776671810",
      "Score": 71,
      "Time": "??:??"
    },
    {
      "Name": "CelestialCrauch",
      "Steam": "76561199808636622",
      "Score": 38,
      "Time": "??:??"
    },
    {
      "Name": "orcohen_x",
      "Steam": "76561199883727460",
      "Score": 35,
      "Time": "18:36"
    }
  ]
}