{
  "Time": "2026-05-24T10:48:38.9114993Z",
  "Players": [
    {
      "Name": "icetea lemon",
      "Steam": "76561199214981522",
      "Score": 66,
      "Time": "82:04"
    },
    {
      "Name": "zuqs",
      "Steam": "76561199193158843",
      "Score": 129,
      "Time": "??:??"
    },
    {
      "Name": "MazniqKrischo",
      "Steam": "76561199054488671",
      "Score": 59,
      "Time": "??:??"
    },
    {
      "Name": "uraganasm1",
      "Steam": "76561198703881590",
      "Score": 28,
      "Time": "??:??"
    },
    {
      "Name": "igaga",
      "Steam": "76561198704351643",
      "Score": 39,
      "Time": "??:??"
    },
    {
      "Name": "ᴛᴀнюхᴀ 2Б",
      "Steam": "76561199748382625",
      "Score": 38,
      "Time": "??:??"
    },
    {
      "Name": "MUWOP",
      "Steam": "76561198701232831",
      "Score": 14,
      "Time": "??:??"
    },
    {
      "Name": "Any",
      "Steam": "76561198034084632",
      "Score": 14,
      "Time": "??:??"
    },
    {
      "Name": "Bogdanuq",
      "Steam": "76561199550122482",
      "Score": 2,
      "Time": "??:??"
    }
  ]
}