{
  "Time": "2026-05-17T14:58:46.6078422Z",
  "Players": [
    {
      "Name": "Unicorn",
      "Steam": "76561199109946506",
      "Score": 0,
      "Time": "224:09"
    },
    {
      "Name": "Monkey",
      "Steam": "76561198712790870",
      "Score": 14,
      "Time": "04:17"
    },
    {
      "Name": "homapafu",
      "Steam": "76561198706197233",
      "Score": 2,
      "Time": "??:??"
    },
    {
      "Name": "ss",
      "Steam": "76561198702309031",
      "Score": 1,
      "Time": "??:??"
    },
    {
      "Name": "SolderPL",
      "Steam": "76561198721363082",
      "Score": 8,
      "Time": "??:??"
    },
    {
      "Name": "GrandSo",
      "Steam": "76561199407587013",
      "Score": 13,
      "Time": "??:??"
    },
    {
      "Name": "< blank >",
      "Steam": "76561198719573642",
      "Score": 14,
      "Time": "??:??"
    }
  ]
}