{
  "Time": "2026-07-18T12:37:51.7637677Z",
  "Players": [
    {
      "Name": "\"'",
      "Steam": "76561199028888055",
      "Score": 0,
      "Time": "??:??"
    },
    {
      "Name": "davidqq",
      "Steam": "76561197990873485",
      "Score": 4,
      "Time": "??:??"
    },
    {
      "Name": "select",
      "Steam": "76561198764234098",
      "Score": 10,
      "Time": "??:??"
    },
    {
      "Name": "❶\uD83C\uDD5C\uD83C\uDD64\uD83C\uDD62\uD83C\uDD62\uD83C\uDD50❶\uD83C\uDD5C",
      "Steam": "76561198719703493",
      "Score": 2,
      "Time": "04:40"
    },
    {
      "Name": "89dj3kvwa",
      "Steam": "76561199867448648",
      "Score": 7,
      "Time": "??:??"
    },
    {
      "Name": "pris",
      "Steam": "76561199613659431",
      "Score": 0,
      "Time": "??:??"
    }
  ]
}