{
  "Time": "2026-07-23T09:35:40.6308796Z",
  "Players": [
    {
      "Name": "\"'",
      "Steam": "76561199028888055",
      "Score": 0,
      "Time": "??:??"
    },
    {
      "Name": "dutzu",
      "Steam": "76561199675704256",
      "Score": 0,
      "Time": "??:??"
    },
    {
      "Name": "xdtf :3",
      "Steam": "76561199820026340",
      "Score": 10,
      "Time": "??:??"
    },
    {
      "Name": "SO_MA_Y_A",
      "Steam": "76561198719703493",
      "Score": 14,
      "Time": "??:??"
    },
    {
      "Name": "Penic_OZ",
      "Steam": "76561199231606074",
      "Score": 10,
      "Time": "16:33"
    },
    {
      "Name": ".gg/permgreen",
      "Steam": "76561198777833988",
      "Score": 11,
      "Time": "21:38"
    },
    {
      "Name": "MgK_Sefu$$",
      "Steam": "76561199501139675",
      "Score": 3,
      "Time": "??:??"
    },
    {
      "Name": "sm",
      "Steam": "76561199521424333",
      "Score": 2,
      "Time": "??:??"
    }
  ]
}