{
  "Time": "2026-05-29T22:01:22.999573Z",
  "Players": [
    {
      "Name": "Nim",
      "Steam": "76561199647822907",
      "Score": 0,
      "Time": "??:??"
    },
    {
      "Name": "Scaredbyy",
      "Steam": "76561199803841652",
      "Score": 12,
      "Time": "??:??"
    },
    {
      "Name": "zeb",
      "Steam": "76561198129364101",
      "Score": 29,
      "Time": "??:??"
    },
    {
      "Name": "o3p8 | hvh noob\uDB40\uDC73 \u1CBC\uDB40\uDC21[ Eos.Core ]",
      "Steam": "76561198793052392",
      "Score": 8,
      "Time": "242:14"
    },
    {
      "Name": "adwwdaadwdawd",
      "Steam": "76561199405626268",
      "Score": 13,
      "Time": "??:??"
    },
    {
      "Name": "PALESTINE",
      "Steam": "76561198710074880",
      "Score": 16,
      "Time": "05:56"
    },
    {
      "Name": "gime da lighter",
      "Steam": "76561198402164823",
      "Score": 46,
      "Time": "49:38"
    },
    {
      "Name": "Cipri 120hz",
      "Steam": "76561199197586731",
      "Score": 15,
      "Time": "??:??"
    },
    {
      "Name": "angel",
      "Steam": "76561199798812373",
      "Score": 13,
      "Time": "??:??"
    },
    {
      "Name": "extrapolation abuse",
      "Steam": "76561198720362972",
      "Score": 63,
      "Time": "??:??"
    },
    {
      "Name": "Lx",
      "Steam": "76561199737816918",
      "Score": 11,
      "Time": "??:??"
    },
    {
      "Name": "elijah",
      "Steam": "76561198201927715",
      "Score": 12,
      "Time": "??:??"
    },
    {
      "Name": "dion2k",
      "Steam": "76561199867058470",
      "Score": 11,
      "Time": "??:??"
    },
    {
      "Name": "GPR3",
      "Steam": "76561198832028178",
      "Score": 59,
      "Time": "153:07"
    },
    {
      "Name": "Eduard",
      "Steam": "76561198848350663",
      "Score": 9,
      "Time": "??:??"
    },
    {
      "Name": "-.-",
      "Steam": "76561199884966036",
      "Score": 35,
      "Time": "??:??"
    }
  ]
}