{
  "Time": "2026-05-20T11:08:14.3601835Z",
  "Players": [
    {
      "Name": "Nim",
      "Steam": "76561199647822907",
      "Score": 0,
      "Time": "??:??"
    },
    {
      "Name": "pasi",
      "Steam": "76561198732676517",
      "Score": 29,
      "Time": "??:??"
    },
    {
      "Name": "◣_◢ iwfc ◣_◢",
      "Steam": "76561198703436589",
      "Score": 39,
      "Time": "??:??"
    },
    {
      "Name": "axure",
      "Steam": "76561199136389558",
      "Score": 59,
      "Time": "??:??"
    },
    {
      "Name": "zuqs",
      "Steam": "76561199193158843",
      "Score": 65,
      "Time": "71:26"
    },
    {
      "Name": "lumeon. ohto y",
      "Steam": "76561198325992067",
      "Score": 33,
      "Time": "??:??"
    }
  ]
}