{
  "Time": "2026-05-18T21:11:00.1467924Z",
  "Players": [
    {
      "Name": "Delta",
      "Steam": "76561199001105777",
      "Score": 0,
      "Time": "25:30"
    },
    {
      "Name": "Burger Enjoyer",
      "Steam": "76561198714884241",
      "Score": 0,
      "Time": "??:??"
    },
    {
      "Name": "Roma",
      "Steam": "76561199874070115",
      "Score": 2,
      "Time": "??:??"
    },
    {
      "Name": "tripleo48 cause ur bannedd ha",
      "Steam": "76561198705383071",
      "Score": 0,
      "Time": "11:02"
    },
    {
      "Name": "bloggo",
      "Steam": "76561198712611951",
      "Score": 3,
      "Time": "??:??"
    },
    {
      "Name": "Curby",
      "Steam": "76561198369113089",
      "Score": 0,
      "Time": "??:??"
    },
    {
      "Name": "hi6w",
      "Steam": "76561199321403005",
      "Score": 0,
      "Time": "??:??"
    },
    {
      "Name": "uhh? | Fixing cfg",
      "Steam": "76561199453255014",
      "Score": 3,
      "Time": "09:48"
    },
    {
      "Name": ".",
      "Steam": "76561198708860550",
      "Score": 1,
      "Time": "??:??"
    },
    {
      "Name": "hu326050",
      "Steam": "76561198759895528",
      "Score": 0,
      "Time": "12:34"
    },
    {
      "Name": "Crimson King",
      "Steam": "76561199377615961",
      "Score": 2,
      "Time": "07:04"
    },
    {
      "Name": "Dodobird",
      "Steam": "76561199889163804",
      "Score": 4,
      "Time": "14:29"
    }
  ]
}