{
  "Time": "2026-06-11T00:48:56.6240418Z",
  "Players": [
    {
      "Name": "kacorvixon",
      "Steam": "76561199507655685",
      "Score": 9,
      "Time": "02:45"
    },
    {
      "Name": "hellen wong",
      "Steam": "76561198960721394",
      "Score": 23,
      "Time": "193:44"
    },
    {
      "Name": "Vicious Beta",
      "Steam": "76561198700071912",
      "Score": 38,
      "Time": "84:29"
    },
    {
      "Name": "shyne",
      "Steam": "76561199096113124",
      "Score": 0,
      "Time": "32:02"
    },
    {
      "Name": "one+",
      "Steam": "76561199442363655",
      "Score": 24,
      "Time": "16:52"
    },
    {
      "Name": "okwhatsnew",
      "Steam": "76561199674442809",
      "Score": 41,
      "Time": "13:49"
    },
    {
      "Name": "yanrewatching",
      "Steam": "76561198701366920",
      "Score": 0,
      "Time": "41:33"
    },
    {
      "Name": "Gurbasch",
      "Steam": "76561198691215062",
      "Score": 0,
      "Time": "21:17"
    },
    {
      "Name": "vivisu",
      "Steam": "76561199793656533",
      "Score": 3,
      "Time": "??:??"
    }
  ]
}