{
  "Time": "2026-06-29T01:02:59.9260061Z",
  "Players": [
    {
      "Name": "7",
      "Steam": "76561198776685602",
      "Score": 18,
      "Time": "??:??"
    },
    {
      "Name": "\uDB40\uDC21\uDB40\uDC21",
      "Steam": "76561198751883888",
      "Score": 4,
      "Time": "01:38"
    },
    {
      "Name": "illinois™",
      "Steam": "76561198787031314",
      "Score": 10,
      "Time": "294:24"
    },
    {
      "Name": "KJVNT",
      "Steam": "76561199242698406",
      "Score": 2,
      "Time": "??:??"
    },
    {
      "Name": "sdb",
      "Steam": "76561198703392706",
      "Score": 8,
      "Time": "??:??"
    },
    {
      "Name": "declan",
      "Steam": "76561198689954481",
      "Score": 0,
      "Time": "02:11"
    },
    {
      "Name": "s-ckaza4",
      "Steam": "76561198687563988",
      "Score": 0,
      "Time": "09:30"
    },
    {
      "Name": "soon",
      "Steam": "76561199889408603",
      "Score": 7,
      "Time": "77:22"
    },
    {
      "Name": "notzonticx",
      "Steam": "76561199729277028",
      "Score": 2,
      "Time": "19:46"
    },
    {
      "Name": "riotsurge",
      "Steam": "76561198734560736",
      "Score": 0,
      "Time": "??:??"
    },
    {
      "Name": "Junior .",
      "Steam": "76561199836886163",
      "Score": 6,
      "Time": "06:16"
    },
    {
      "Name": "\uD83D\uDDFF⃤⃢ B",
      "Steam": "76561197973605723",
      "Score": 3,
      "Time": "341:24"
    },
    {
      "Name": "supertropin",
      "Steam": "76561199273885139",
      "Score": 0,
      "Time": "370:40"
    },
    {
      "Name": "Huh?",
      "Steam": "76561198733635580",
      "Score": 0,
      "Time": "??:??"
    },
    {
      "Name": "NXC | ShadowSpecter",
      "Steam": "76561198748012660",
      "Score": 9,
      "Time": "16:02"
    }
  ]
}