{
  "Time": "2026-06-24T18:39:49.6496021Z",
  "Players": [
    {
      "Name": "first time on gamesense.pub",
      "Steam": "76561198687374799",
      "Score": 77,
      "Time": "24:42"
    },
    {
      "Name": "big ass penguin",
      "Steam": "76561199387058491",
      "Score": 24,
      "Time": "02:06"
    },
    {
      "Name": "wait no way!",
      "Steam": "76561199411523950",
      "Score": 35,
      "Time": "18:45"
    },
    {
      "Name": "silk",
      "Steam": "76561198734736041",
      "Score": 56,
      "Time": "188:23"
    },
    {
      "Name": "Vicious",
      "Steam": "76561198700071912",
      "Score": 101,
      "Time": "??:??"
    },
    {
      "Name": "Jack",
      "Steam": "76561198702881176",
      "Score": 65,
      "Time": "163:58"
    },
    {
      "Name": "The best fatal user",
      "Steam": "76561199814724137",
      "Score": 0,
      "Time": "01:26"
    },
    {
      "Name": "notzonticx",
      "Steam": "76561199729277028",
      "Score": 60,
      "Time": "253:49"
    },
    {
      "Name": "hanginonnacrane",
      "Steam": "76561199096269503",
      "Score": 23,
      "Time": "36:20"
    }
  ]
}