{
  "Time": "2026-04-10T04:57:52.6672919Z",
  "Players": [
    {
      "Name": "brr brr patapim",
      "Steam": "76561199880678892",
      "Score": 3,
      "Time": "??:??"
    },
    {
      "Name": "woofwoofmeow123",
      "Steam": "76561198180065165",
      "Score": 2,
      "Time": "75:16"
    },
    {
      "Name": "LeaLea",
      "Steam": "76561199319414622",
      "Score": 44,
      "Time": "16:09"
    },
    {
      "Name": "IntelBroker #lowcortisol",
      "Steam": "76561199050170734",
      "Score": 56,
      "Time": "43:42"
    },
    {
      "Name": "Bot Prance",
      "Steam": "76561198770610794",
      "Score": 83,
      "Time": "??:??"
    },
    {
      "Name": "DXVXD",
      "Steam": "76561199442363655",
      "Score": 58,
      "Time": "??:??"
    },
    {
      "Name": "im a immigrant",
      "Steam": "76561199410751476",
      "Score": 49,
      "Time": "02:07"
    },
    {
      "Name": "Way 2 Sexy",
      "Steam": "76561199156395215",
      "Score": 77,
      "Time": "44:45"
    },
    {
      "Name": "magehack",
      "Steam": "76561198999235985",
      "Score": 50,
      "Time": "258:19"
    },
    {
      "Name": "C@SS",
      "Steam": "76561198127862296",
      "Score": 2,
      "Time": "01:59"
    },
    {
      "Name": "y",
      "Steam": "76561199837114653",
      "Score": 36,
      "Time": "76:19"
    },
    {
      "Name": "gerbert",
      "Steam": "76561199803883011",
      "Score": 0,
      "Time": "718:01"
    }
  ]
}