{
  "Time": "2026-03-21T05:01:38.6279187Z",
  "Players": [
    {
      "Name": "imnotpig",
      "Steam": "76561199158419168",
      "Score": 4,
      "Time": "11:21"
    },
    {
      "Name": "WhyYouCheating™",
      "Steam": "76561199750075849",
      "Score": 101,
      "Time": "??:??"
    },
    {
      "Name": "\uDB40\uDC21\uDB40\uDC21",
      "Steam": "76561199031753721",
      "Score": 55,
      "Time": "??:??"
    },
    {
      "Name": "XXⅠ",
      "Steam": "76561198762281843",
      "Score": 81,
      "Time": "??:??"
    },
    {
      "Name": "✞OC✞",
      "Steam": "76561198772153840",
      "Score": 2,
      "Time": "03:15"
    },
    {
      "Name": "K",
      "Steam": "76561198787397270",
      "Score": 88,
      "Time": "40:57"
    },
    {
      "Name": "imnotdoggo",
      "Steam": "76561199140462879",
      "Score": 85,
      "Time": "29:25"
    }
  ]
}