{
  "Time": "2026-05-05T18:27:23.2822123Z",
  "Players": [
    {
      "Name": "ofhAFNujawuiy",
      "Steam": "76561199765066337",
      "Score": 6,
      "Time": "??:??"
    },
    {
      "Name": "BonQEQE",
      "Steam": "76561198418443435",
      "Score": 136,
      "Time": "106:48"
    },
    {
      "Name": "Myno",
      "Steam": "76561199085317045",
      "Score": 100,
      "Time": "??:??"
    },
    {
      "Name": "stszk",
      "Steam": "76561199407935025",
      "Score": 110,
      "Time": "??:??"
    },
    {
      "Name": "Codaxy",
      "Steam": "76561198144469869",
      "Score": 56,
      "Time": "??:??"
    },
    {
      "Name": "NOMI",
      "Steam": "76561199427399372",
      "Score": 1,
      "Time": "??:??"
    },
    {
      "Name": "enhance",
      "Steam": "76561198386911787",
      "Score": 34,
      "Time": "??:??"
    }
  ]
}