{
  "Time": "2026-03-21T02:23:38.6184487Z",
  "Players": [
    {
      "Name": "76561198791368162",
      "Steam": "76561198791368162",
      "Score": 26,
      "Time": "??:??"
    },
    {
      "Name": "christian cortez",
      "Steam": "76561198756303634",
      "Score": 0,
      "Time": "95:21"
    },
    {
      "Name": "im a immigrant",
      "Steam": "76561199410751476",
      "Score": 35,
      "Time": "88:00"
    },
    {
      "Name": ":3",
      "Steam": "76561198744847839",
      "Score": 13,
      "Time": "06:18"
    },
    {
      "Name": "shitbot",
      "Steam": "76561198741458634",
      "Score": 5,
      "Time": "??:??"
    },
    {
      "Name": "cookies",
      "Steam": "76561199740544730",
      "Score": 0,
      "Time": "??:??"
    },
    {
      "Name": "imnotdoggo",
      "Steam": "76561199140462879",
      "Score": 21,
      "Time": "??:??"
    }
  ]
}