{
  "Time": "2026-06-02T22:51:17.9354401Z",
  "Players": [
    {
      "Name": "rope",
      "Steam": "76561198332515437",
      "Score": 32,
      "Time": "14:14"
    },
    {
      "Name": "castle | Big Namer",
      "Steam": "76561198122916495",
      "Score": 0,
      "Time": "10:03"
    },
    {
      "Name": "ajjhuwim082",
      "Steam": "76561199701659337",
      "Score": 18,
      "Time": "??:??"
    },
    {
      "Name": "Noki",
      "Steam": "76561198729323702",
      "Score": 0,
      "Time": "219:01"
    },
    {
      "Name": "yanrewatching",
      "Steam": "76561198701366920",
      "Score": 34,
      "Time": "22:11"
    },
    {
      "Name": "Agony",
      "Steam": "76561198735582746",
      "Score": 86,
      "Time": "36:04"
    },
    {
      "Name": "1",
      "Steam": "76561199680874612",
      "Score": 50,
      "Time": "53:35"
    },
    {
      "Name": "skoobert",
      "Steam": "76561199359618052",
      "Score": 9,
      "Time": "24:41"
    },
    {
      "Name": "Big Bang",
      "Steam": "76561198739568756",
      "Score": 29,
      "Time": "??:??"
    },
    {
      "Name": "grief",
      "Steam": "76561199685683520",
      "Score": 25,
      "Time": "23:51"
    }
  ]
}