{
  "Time": "2026-04-24T16:09:28.2319383Z",
  "Players": [
    {
      "Name": "[ am ]",
      "Steam": "76561199187190389",
      "Score": 87,
      "Time": "??:??"
    },
    {
      "Name": "SypherXz",
      "Steam": "76561199624274699",
      "Score": 19,
      "Time": "??:??"
    },
    {
      "Name": "P",
      "Steam": "76561199828563808",
      "Score": 24,
      "Time": "??:??"
    },
    {
      "Name": "imnotdoggo",
      "Steam": "76561199140462879",
      "Score": 21,
      "Time": "??:??"
    }
  ]
}