{
  "Time": "2026-05-05T17:32:36.482222Z",
  "Players": [
    {
      "Name": "moon",
      "Steam": "76561199676449396",
      "Score": 57,
      "Time": "??:??"
    },
    {
      "Name": "trascavlad2008",
      "Steam": "76561199870646030",
      "Score": 49,
      "Time": "??:??"
    },
    {
      "Name": "Darfushkaaa<3",
      "Steam": "76561198767283357",
      "Score": 62,
      "Time": "??:??"
    },
    {
      "Name": "Fishie",
      "Steam": "76561198727266652",
      "Score": 23,
      "Time": "??:??"
    },
    {
      "Name": "meow meow",
      "Steam": "76561199828015418",
      "Score": 13,
      "Time": "??:??"
    },
    {
      "Name": "ko271443",
      "Steam": "76561199849580431",
      "Score": 0,
      "Time": "??:??"
    }
  ]
}