{
  "Time": "2026-02-24T18:36:43.0204084Z",
  "Players": [
    {
      "Name": "PI",
      "Steam": "76561199148908407",
      "Score": 5,
      "Time": "07:23"
    },
    {
      "Name": "abyss",
      "Steam": "76561198766995890",
      "Score": 16,
      "Time": "??:??"
    },
    {
      "Name": "static",
      "Steam": "76561198180564201",
      "Score": 15,
      "Time": "??:??"
    },
    {
      "Name": "LoveDontStop",
      "Steam": "76561198230741068",
      "Score": 4,
      "Time": "??:??"
    }
  ]
}