{
  "Time": "2026-01-17T21:35:08.1606703Z",
  "Players": [
    {
      "Name": "GESHTALT",
      "Steam": "76561198317554443",
      "Score": 20,
      "Time": "363:32"
    },
    {
      "Name": "Gertt-01",
      "Steam": "76561198753907050",
      "Score": 26,
      "Time": "??:??"
    },
    {
      "Name": "ᵏᵒᵖᶠᵗʳᶦᵗᵗglobal",
      "Steam": "76561197963250432",
      "Score": 57,
      "Time": "23:42"
    },
    {
      "Name": "ghostY",
      "Steam": "76561199591486018",
      "Score": 17,
      "Time": "608:06"
    },
    {
      "Name": "ᵏᵒᵖᶠᵗʳᶦᵗᵗglobal",
      "Steam": "76561197963183861",
      "Score": 0,
      "Time": "150:12"
    },
    {
      "Name": "u",
      "Steam": "76561199803082526",
      "Score": 50,
      "Time": "??:??"
    },
    {
      "Name": "ᵏᵒᵖᶠᵗʳᶦᵗᵗglobal",
      "Steam": "76561198341012123",
      "Score": 45,
      "Time": "284:15"
    },
    {
      "Name": "sea kyle",
      "Steam": "76561198759829672",
      "Score": 41,
      "Time": "??:??"
    },
    {
      "Name": "sebby >.<",
      "Steam": "76561198874356385",
      "Score": 5,
      "Time": "??:??"
    },
    {
      "Name": "SW",
      "Steam": "76561199647822907",
      "Score": 0,
      "Time": "??:??"
    },
    {
      "Name": "GESHTALT",
      "Steam": "76561198151423700",
      "Score": 62,
      "Time": "112:15"
    },
    {
      "Name": "GESHTALT",
      "Steam": "76561199790878653",
      "Score": 3,
      "Time": "07:48"
    },
    {
      "Name": "710xb7",
      "Steam": "76561199401111003",
      "Score": 18,
      "Time": "??:??"
    },
    {
      "Name": "Gertt-01",
      "Steam": "76561198756919457",
      "Score": 2,
      "Time": "42:53"
    }
  ]
}