{
  "Time": "2026-01-11T17:39:31.6318434Z",
  "Players": [
    {
      "Name": "i like feet",
      "Steam": "76561199849233696",
      "Score": 24,
      "Time": "??:??"
    },
    {
      "Name": "Lukynvoe.GG",
      "Steam": "76561199373698729",
      "Score": 12,
      "Time": "08:33"
    },
    {
      "Name": "nohvhplz",
      "Steam": "76561199827618693",
      "Score": 34,
      "Time": "09:00"
    },
    {
      "Name": "wowosdgffds",
      "Steam": "76561198747447744",
      "Score": 32,
      "Time": "??:??"
    }
  ]
}