{
  "Time": "2026-01-13T14:19:14.4073263Z",
  "Players": [
    {
      "Name": "tymo--",
      "Steam": "76561199425592793",
      "Score": 79,
      "Time": "25:22"
    },
    {
      "Name": "ghostY",
      "Steam": "76561199591486018",
      "Score": 80,
      "Time": "30:36"
    },
    {
      "Name": "anthonywin219",
      "Steam": "76561198768850609",
      "Score": 0,
      "Time": "??:??"
    },
    {
      "Name": "alr",
      "Steam": "76561199884481365",
      "Score": 4,
      "Time": "07:44"
    },
    {
      "Name": "I1I1I1I1I1I1",
      "Steam": "76561199803082526",
      "Score": 2,
      "Time": "04:55"
    },
    {
      "Name": "\uD835\uDE56\uD835\uDE60\uD835\uDE5E",
      "Steam": "76561198784581696",
      "Score": 64,
      "Time": "43:35"
    },
    {
      "Name": "ᴄᴏʀᴏɴᴀ",
      "Steam": "76561199180147646",
      "Score": 34,
      "Time": "710:24"
    },
    {
      "Name": "Devo",
      "Steam": "76561198755398524",
      "Score": 109,
      "Time": "33:56"
    },
    {
      "Name": "CarlitoMB",
      "Steam": "76561199697633072",
      "Score": 0,
      "Time": "02:32"
    },
    {
      "Name": "SW",
      "Steam": "76561199647822907",
      "Score": 0,
      "Time": "??:??"
    },
    {
      "Name": "gelgmire",
      "Steam": "76561199560217782",
      "Score": 9,
      "Time": "32:35"
    },
    {
      "Name": "cheating in hvh",
      "Steam": "76561199866887764",
      "Score": 48,
      "Time": "12:42"
    },
    {
      "Name": "Ferox",
      "Steam": "76561199377440484",
      "Score": 7,
      "Time": "1088:56"
    }
  ]
}