{
  "Time": "2026-01-24T03:32:34.2647602Z",
  "Players": [
    {
      "Name": "dhali",
      "Steam": "76561198745799920",
      "Score": 0,
      "Time": "00:47"
    },
    {
      "Name": "angel",
      "Steam": "76561199798812373",
      "Score": 0,
      "Time": "??:??"
    },
    {
      "Name": "Felix",
      "Steam": "76561198193603937",
      "Score": 0,
      "Time": "311:47"
    },
    {
      "Name": "Trav",
      "Steam": "76561199471217940",
      "Score": 13,
      "Time": "13:03"
    },
    {
      "Name": "fa \uDB40\uDC21\uDB40\uDC21",
      "Steam": "76561198152322242",
      "Score": 0,
      "Time": "??:??"
    },
    {
      "Name": "Turtle.Turn(6)",
      "Steam": "76561199187600654",
      "Score": 2,
      "Time": "02:25"
    },
    {
      "Name": ";pooh shiesty",
      "Steam": "76561199040449208",
      "Score": 14,
      "Time": "??:??"
    },
    {
      "Name": "\"'",
      "Steam": "76561199028888055",
      "Score": 0,
      "Time": "??:??"
    },
    {
      "Name": "stylisz",
      "Steam": "76561199683040816",
      "Score": 6,
      "Time": "18:38"
    }
  ]
}