{
  "Time": "2026-01-29T22:38:48.3227708Z",
  "Players": [
    {
      "Name": "6 MILLION?",
      "Steam": "76561198774939761",
      "Score": 8,
      "Time": "??:??"
    },
    {
      "Name": "Niko88",
      "Steam": "76561198997172050",
      "Score": 36,
      "Time": "??:??"
    },
    {
      "Name": ".50 cal⁧⁧ to my head",
      "Steam": "76561199042221496",
      "Score": 30,
      "Time": "??:??"
    },
    {
      "Name": "siegmund",
      "Steam": "76561198743712610",
      "Score": 31,
      "Time": "06:05"
    },
    {
      "Name": "Infantrit",
      "Steam": "76561199827876555",
      "Score": 63,
      "Time": "??:??"
    }
  ]
}