{
  "Time": "2026-01-30T14:18:38.1751819Z",
  "Players": [
    {
      "Name": "Tye",
      "Steam": "76561199447283446",
      "Score": 0,
      "Time": "??:??"
    },
    {
      "Name": "Pakas Biseks",
      "Steam": "76561199892316246",
      "Score": 26,
      "Time": "25:36"
    },
    {
      "Name": "jooousy",
      "Steam": "76561198745935413",
      "Score": 4,
      "Time": "07:49"
    },
    {
      "Name": "aimjunkies update",
      "Steam": "76561199660705672",
      "Score": 4,
      "Time": "??:??"
    },
    {
      "Name": "Farifadir Kambuira",
      "Steam": "76561198744415997",
      "Score": 30,
      "Time": "??:??"
    },
    {
      "Name": "suse",
      "Steam": "76561198335217105",
      "Score": 6,
      "Time": "??:??"
    }
  ]
}