{
  "Time": "2025-12-13T21:37:09.5382255Z",
  "Players": [
    {
      "Name": "takahiroryuu",
      "Steam": "76561199233058634",
      "Score": 22,
      "Time": "23:45"
    },
    {
      "Name": "SW",
      "Steam": "76561199647822907",
      "Score": 0,
      "Time": "286:48"
    },
    {
      "Name": "ᵏᵒᵖᶠᵗʳᶦᵗᵗqueue",
      "Steam": "76561198341012123",
      "Score": 4,
      "Time": "02:41"
    },
    {
      "Name": "Malac Greznar",
      "Steam": "76561198784167090",
      "Score": 1,
      "Time": "463:31"
    },
    {
      "Name": "kuys",
      "Steam": "76561198353681360",
      "Score": 15,
      "Time": "201:07"
    },
    {
      "Name": "ferox",
      "Steam": "76561199377440484",
      "Score": 17,
      "Time": "23:04"
    },
    {
      "Name": "anthonywin219",
      "Steam": "76561198768850609",
      "Score": 0,
      "Time": "??:??"
    },
    {
      "Name": "Lol",
      "Steam": "76561198760858650",
      "Score": 5,
      "Time": "??:??"
    },
    {
      "Name": "l0l1p0pa",
      "Steam": "76561198765191086",
      "Score": 4,
      "Time": "147:22"
    },
    {
      "Name": "Nixware user",
      "Steam": "76561199820198006",
      "Score": 8,
      "Time": "323:14"
    },
    {
      "Name": "^^^^^^^xD",
      "Steam": "76561198131709407",
      "Score": 21,
      "Time": "25:51"
    },
    {
      "Name": "soundcloud rapper",
      "Steam": "76561198160571123",
      "Score": 23,
      "Time": "266:49"
    },
    {
      "Name": "mdnzaa",
      "Steam": "76561198759626012",
      "Score": 5,
      "Time": "11:54"
    },
    {
      "Name": "Lobo Negro",
      "Steam": "76561199867045110",
      "Score": 17,
      "Time": "19:47"
    },
    {
      "Name": "XxDemon_FaZe420xX",
      "Steam": "76561199889658926",
      "Score": 4,
      "Time": "177:43"
    },
    {
      "Name": "0MEH",
      "Steam": "76561198418699703",
      "Score": 0,
      "Time": "92:26"
    },
    {
      "Name": "! xgrc ⋆｡°✩",
      "Steam": "76561198791116856",
      "Score": 30,
      "Time": "160:36"
    },
    {
      "Name": "\"\u1CBC\u1CBC\u1CBC\u1CBC\u1CBC\u1CBC\u1CBC\u1CBC\u1CBC\"",
      "Steam": "76561198832028178",
      "Score": 6,
      "Time": "160:14"
    },
    {
      "Name": "Panda",
      "Steam": "76561198453141846",
      "Score": 14,
      "Time": "181:06"
    }
  ]
}