{
  "Time": "2025-11-06T23:36:00.9360018Z",
  "Players": [
    {
      "Name": "uiy",
      "Steam": "76561199276906809",
      "Score": 14,
      "Time": "21:57"
    },
    {
      "Name": "Bhg",
      "Steam": "76561199647822907",
      "Score": 0,
      "Time": "??:??"
    },
    {
      "Name": "★Titsoutkickedout★",
      "Steam": "76561198124007805",
      "Score": 13,
      "Time": "??:??"
    },
    {
      "Name": "Seiðr",
      "Steam": "76561198333235279",
      "Score": 22,
      "Time": "564:35"
    },
    {
      "Name": "Changed",
      "Steam": "76561198151409110",
      "Score": 0,
      "Time": "??:??"
    },
    {
      "Name": "brazilian but liefte",
      "Steam": "76561198781748052",
      "Score": 2,
      "Time": "266:10"
    },
    {
      "Name": "Ugy",
      "Steam": "76561198274193245",
      "Score": 2,
      "Time": "??:??"
    }
  ]
}