{
  "Time": "2025-12-25T18:22:57.3620557Z",
  "Players": [
    {
      "Name": "\"'",
      "Steam": "76561199028888055",
      "Score": 0,
      "Time": "??:??"
    },
    {
      "Name": "Metky",
      "Steam": "76561199848062599",
      "Score": 0,
      "Time": "??:??"
    },
    {
      "Name": "Qrazzy",
      "Steam": "76561198279109727",
      "Score": 7,
      "Time": "??:??"
    },
    {
      "Name": "Hwid",
      "Steam": "76561199552312261",
      "Score": 0,
      "Time": "76:55"
    },
    {
      "Name": "BIG mommy",
      "Steam": "76561198757298990",
      "Score": 5,
      "Time": "05:51"
    },
    {
      "Name": "duck1",
      "Steam": "76561198905036845",
      "Score": 7,
      "Time": "??:??"
    },
    {
      "Name": "pulasmakerpek",
      "Steam": "76561199737490201",
      "Score": 4,
      "Time": "??:??"
    },
    {
      "Name": "kizaru fonat",
      "Steam": "76561199387971882",
      "Score": 2,
      "Time": "01:31"
    },
    {
      "Name": "boredtap.su alpha member",
      "Steam": "76561199756507474",
      "Score": 2,
      "Time": "??:??"
    },
    {
      "Name": "brodie",
      "Steam": "76561199311106586",
      "Score": 0,
      "Time": "05:01"
    }
  ]
}