{
  "Time": "2025-12-02T19:28:27.6235376Z",
  "Players": [
    {
      "Name": "yung",
      "Steam": "76561199210685295",
      "Score": 14,
      "Time": "04:35"
    },
    {
      "Name": "unlimitedminds",
      "Steam": "76561198764844454",
      "Score": 10,
      "Time": "07:44"
    },
    {
      "Name": "Nigger Tiocfaidharla",
      "Steam": "76561198788061697",
      "Score": 4,
      "Time": "11:10"
    },
    {
      "Name": "aueshkavnezakona",
      "Steam": "76561199016369605",
      "Score": 0,
      "Time": "??:??"
    }
  ]
}