{
  "Time": "2025-11-14T13:59:29.0401411Z",
  "Players": [
    {
      "Name": "\"'",
      "Steam": "76561199028888055",
      "Score": 0,
      "Time": "??:??"
    },
    {
      "Name": "3.3",
      "Steam": "76561199816923872",
      "Score": 14,
      "Time": "??:??"
    },
    {
      "Name": "iwashdishes1337",
      "Steam": "76561198777483174",
      "Score": 14,
      "Time": "??:??"
    },
    {
      "Name": "lr084281",
      "Steam": "76561199865752493",
      "Score": 0,
      "Time": "??:??"
    },
    {
      "Name": "exceLLenT. ︻芫=一",
      "Steam": "76561198350146465",
      "Score": 10,
      "Time": "??:??"
    },
    {
      "Name": "ava",
      "Steam": "76561198843347921",
      "Score": 55,
      "Time": "64:27"
    },
    {
      "Name": "\uD835\uDD05\uD835\uDD1E\uD835\uDD30\uD835\uDD31\uD835\uDD1E\uD835\uDD2F\uD835\uDD21",
      "Steam": "76561199827217325",
      "Score": 46,
      "Time": "60:21"
    }
  ]
}