{
  "Time": "2025-10-31T11:56:09.8450091Z",
  "Players": [
    {
      "Name": "\"'",
      "Steam": "76561199028888055",
      "Score": 0,
      "Time": "95:24"
    },
    {
      "Name": "Rupertgamingboy",
      "Steam": "76561198835474175",
      "Score": 6,
      "Time": "33:19"
    },
    {
      "Name": "MiC",
      "Steam": "76561199484750150",
      "Score": 10,
      "Time": "24:01"
    },
    {
      "Name": "essets",
      "Steam": "76561199864295000",
      "Score": 7,
      "Time": "??:??"
    },
    {
      "Name": "ze66y",
      "Steam": "76561199175953224",
      "Score": 6,
      "Time": "??:??"
    },
    {
      "Name": "MilkyWay",
      "Steam": "76561199712229477",
      "Score": 3,
      "Time": "??:??"
    },
    {
      "Name": "Jake",
      "Steam": "76561198288868796",
      "Score": 6,
      "Time": "??:??"
    }
  ]
}