{
  "Time": "2025-12-01T13:32:16.0994718Z",
  "Players": [
    {
      "Name": "SW",
      "Steam": "76561199647822907",
      "Score": 0,
      "Time": "??:??"
    },
    {
      "Name": "fr1fx",
      "Steam": "76561199042138318",
      "Score": 29,
      "Time": "??:??"
    },
    {
      "Name": "bekonn",
      "Steam": "76561198877421988",
      "Score": 18,
      "Time": "72:37"
    },
    {
      "Name": "ʎssndɐןןı̣uɐʌ",
      "Steam": "76561198311232875",
      "Score": 6,
      "Time": "??:??"
    },
    {
      "Name": "Fake",
      "Steam": "76561199729334552",
      "Score": 0,
      "Time": "??:??"
    },
    {
      "Name": "godking01091901019",
      "Steam": "76561199502340331",
      "Score": 17,
      "Time": "68:58"
    },
    {
      "Name": "toozy",
      "Steam": "76561197963250432",
      "Score": 32,
      "Time": "23:35"
    },
    {
      "Name": "cheat boosted",
      "Steam": "76561199482346717",
      "Score": 0,
      "Time": "??:??"
    },
    {
      "Name": "x",
      "Steam": "76561197962872195",
      "Score": 18,
      "Time": "36:30"
    },
    {
      "Name": "miLo-dA-K1nG",
      "Steam": "76561198763804875",
      "Score": 2,
      "Time": "19:00"
    },
    {
      "Name": "?oneetap?",
      "Steam": "76561199759033501",
      "Score": 4,
      "Time": "??:??"
    },
    {
      "Name": "WSH",
      "Steam": "76561199647816559",
      "Score": 0,
      "Time": "??:??"
    },
    {
      "Name": "thefinest",
      "Steam": "76561199855905772",
      "Score": 10,
      "Time": "04:37"
    }
  ]
}