{
  "Time": "2025-12-25T13:26:59.8234826Z",
  "Players": [
    {
      "Name": "The Lion",
      "Steam": "76561199482148640",
      "Score": 77,
      "Time": "??:??"
    },
    {
      "Name": "x64",
      "Steam": "76561198907544142",
      "Score": 30,
      "Time": "??:??"
    },
    {
      "Name": "AIMWARE.CC",
      "Steam": "76561198754676427",
      "Score": 0,
      "Time": "??:??"
    },
    {
      "Name": "sano60x",
      "Steam": "76561199618384347",
      "Score": 4,
      "Time": "??:??"
    }
  ]
}