{
  "Time": "2025-12-11T11:27:17.4707457Z",
  "Players": [
    {
      "Name": "catboy",
      "Steam": "76561199798812373",
      "Score": 0,
      "Time": "72:31"
    },
    {
      "Name": "Nikos",
      "Steam": "76561198957724883",
      "Score": 36,
      "Time": "11:17"
    },
    {
      "Name": "ᵏᵒᵖᶠᵗʳᶦᵗᵗSeiðr",
      "Steam": "76561198333235279",
      "Score": 166,
      "Time": "??:??"
    },
    {
      "Name": "CHAMPIONS [BOTTIK]",
      "Steam": "76561199319679407",
      "Score": 0,
      "Time": "??:??"
    },
    {
      "Name": "perception",
      "Steam": "76561199854714392",
      "Score": 133,
      "Time": "??:??"
    },
    {
      "Name": "ferox",
      "Steam": "76561199377440484",
      "Score": 99,
      "Time": "??:??"
    },
    {
      "Name": "MCV",
      "Steam": "76561198759772418",
      "Score": 20,
      "Time": "24:10"
    },
    {
      "Name": "batman",
      "Steam": "76561199863010741",
      "Score": 54,
      "Time": "??:??"
    },
    {
      "Name": "☽",
      "Steam": "76561199680474626",
      "Score": 84,
      "Time": "??:??"
    },
    {
      "Name": "Bot Milo",
      "Steam": "76561198763300968",
      "Score": 45,
      "Time": "??:??"
    },
    {
      "Name": "N111 =DD",
      "Steam": "76561198842015641",
      "Score": 27,
      "Time": "??:??"
    },
    {
      "Name": "dawg",
      "Steam": "76561199011662523",
      "Score": 14,
      "Time": "??:??"
    },
    {
      "Name": "?",
      "Steam": "76561199631116344",
      "Score": 6,
      "Time": "??:??"
    },
    {
      "Name": "easd0529",
      "Steam": "76561199865022601",
      "Score": 0,
      "Time": "??:??"
    },
    {
      "Name": "( ‾ʖ̫‾)",
      "Steam": "76561199559471982",
      "Score": 3,
      "Time": "??:??"
    },
    {
      "Name": "ozzy",
      "Steam": "76561198400274255",
      "Score": 0,
      "Time": "??:??"
    },
    {
      "Name": "ᵏᵒᵖᶠᵗʳᶦᵗᵗtoozy",
      "Steam": "76561197963250432",
      "Score": 6,
      "Time": "??:??"
    },
    {
      "Name": "Nothing",
      "Steam": "76561199388843433",
      "Score": 0,
      "Time": "??:??"
    }
  ]
}