{
  "Time": "2026-01-05T00:47:29.1572224Z",
  "Players": [
    {
      "Name": "AbduLLaHH",
      "Steam": "76561199781089521",
      "Score": 17,
      "Time": "333:25"
    },
    {
      "Name": "Gertt-01",
      "Steam": "76561198756919457",
      "Score": 2,
      "Time": "76:58"
    },
    {
      "Name": "VikingHammer87",
      "Steam": "76561198001746934",
      "Score": 6,
      "Time": "359:20"
    },
    {
      "Name": "ᵏᵒᵖᶠᵗʳᶦᵗᵗqueue",
      "Steam": "76561198341012123",
      "Score": 47,
      "Time": "80:09"
    },
    {
      "Name": "hrisitosense",
      "Steam": "76561199003552070",
      "Score": 69,
      "Time": "??:??"
    },
    {
      "Name": "anthonywin219",
      "Steam": "76561198768850609",
      "Score": 2,
      "Time": "??:??"
    },
    {
      "Name": "ᵖˡᵃᵍᵘᵉ Jerry",
      "Steam": "76561199750500791",
      "Score": 24,
      "Time": "97:00"
    },
    {
      "Name": "88",
      "Steam": "76561198152231956",
      "Score": 0,
      "Time": "??:??"
    },
    {
      "Name": "SIKINTILI",
      "Steam": "76561198288420989",
      "Score": 59,
      "Time": "38:55"
    },
    {
      "Name": "SIKINTILI",
      "Steam": "76561198201927715",
      "Score": 7,
      "Time": "04:52"
    }
  ]
}