{
  "Time": "2026-03-26T20:50:40.5422193Z",
  "Players": [
    {
      "Name": "\"'",
      "Steam": "76561199028888055",
      "Score": 0,
      "Time": "??:??"
    },
    {
      "Name": "2030 joiner",
      "Steam": "76561198753176325",
      "Score": 16,
      "Time": "04:30"
    },
    {
      "Name": "piggernorn.win",
      "Steam": "76561198772698072",
      "Score": 17,
      "Time": "??:??"
    },
    {
      "Name": "thc",
      "Steam": "76561199221165898",
      "Score": 86,
      "Time": "??:??"
    },
    {
      "Name": "digga",
      "Steam": "76561198743761579",
      "Score": 0,
      "Time": "??:??"
    },
    {
      "Name": "Any",
      "Steam": "76561198034084632",
      "Score": 29,
      "Time": "??:??"
    },
    {
      "Name": "Bread",
      "Steam": "76561199068154041",
      "Score": 0,
      "Time": "??:??"
    },
    {
      "Name": "McLennyFace",
      "Steam": "76561198766795951",
      "Score": 66,
      "Time": "??:??"
    },
    {
      "Name": "ᵈʳᵉᵃᵐˡⁱᵍʰᵗvance",
      "Steam": "76561199889697498",
      "Score": 0,
      "Time": "??:??"
    },
    {
      "Name": "Dez",
      "Steam": "76561199181342269",
      "Score": 147,
      "Time": "111:15"
    }
  ]
}