{
  "Time": "2026-03-18T16:50:14.5441608Z",
  "Players": [
    {
      "Name": "mock",
      "Steam": "76561198755398524",
      "Score": 100,
      "Time": "28:21"
    },
    {
      "Name": "Nim",
      "Steam": "76561199647822907",
      "Score": 0,
      "Time": "??:??"
    },
    {
      "Name": "angel",
      "Steam": "76561199798812373",
      "Score": 57,
      "Time": "26:45"
    },
    {
      "Name": "Melody",
      "Steam": "76561197964253121",
      "Score": 38,
      "Time": "??:??"
    },
    {
      "Name": "☽",
      "Steam": "76561199680474626",
      "Score": 54,
      "Time": "13:19"
    },
    {
      "Name": "Irony Manic",
      "Steam": "76561199690909304",
      "Score": 6,
      "Time": "??:??"
    },
    {
      "Name": "Quickzyyy",
      "Steam": "76561199683605953",
      "Score": 7,
      "Time": "??:??"
    },
    {
      "Name": "coㅤㅤㅤㅤㅤke",
      "Steam": "76561199682061013",
      "Score": 8,
      "Time": "??:??"
    },
    {
      "Name": "i miss eversio",
      "Steam": "76561198734668878",
      "Score": 6,
      "Time": "??:??"
    },
    {
      "Name": "catsssssss",
      "Steam": "76561198794467793",
      "Score": 88,
      "Time": "25:21"
    },
    {
      "Name": "wojtusref",
      "Steam": "76561198730338094",
      "Score": 3,
      "Time": "05:31"
    },
    {
      "Name": "97Bajnokk",
      "Steam": "76561199524640737",
      "Score": 80,
      "Time": "55:22"
    }
  ]
}