{
  "Time": "2026-03-23T10:22:59.2307328Z",
  "Players": [
    {
      "Name": "Nim",
      "Steam": "76561199647822907",
      "Score": 0,
      "Time": "223:54"
    },
    {
      "Name": "Leozinho bala tensa",
      "Steam": "76561198061879584",
      "Score": 2,
      "Time": "??:??"
    },
    {
      "Name": "veronica",
      "Steam": "76561198745723178",
      "Score": 14,
      "Time": "04:41"
    },
    {
      "Name": "godcomplex",
      "Steam": "76561199036333155",
      "Score": 0,
      "Time": "44:42"
    },
    {
      "Name": "0MEH",
      "Steam": "76561198418699703",
      "Score": 78,
      "Time": "??:??"
    },
    {
      "Name": "void",
      "Steam": "76561199503396912",
      "Score": 0,
      "Time": "07:59"
    },
    {
      "Name": "Miri",
      "Steam": "76561199842369196",
      "Score": 2,
      "Time": "??:??"
    },
    {
      "Name": "lukas.riedinger1501",
      "Steam": "76561198724611545",
      "Score": 0,
      "Time": "??:??"
    },
    {
      "Name": "I CANT LIE",
      "Steam": "76561199844633656",
      "Score": 19,
      "Time": "??:??"
    },
    {
      "Name": "ˢᵗᵃʳˡⁱᵍʰᵗfentlover",
      "Steam": "76561199136741331",
      "Score": 4,
      "Time": "69:49"
    }
  ]
}