{
  "Time": "2026-04-27T17:18:54.3742207Z",
  "Players": [
    {
      "Name": "b36b3",
      "Steam": "76561199846633307",
      "Score": 48,
      "Time": "??:??"
    },
    {
      "Name": "YOSHI",
      "Steam": "76561199882241139",
      "Score": 18,
      "Time": "08:50"
    },
    {
      "Name": "ム Keen ム",
      "Steam": "76561198841875201",
      "Score": 0,
      "Time": "??:??"
    },
    {
      "Name": "de_cretin Staszek",
      "Steam": "76561199407935025",
      "Score": 110,
      "Time": "96:11"
    },
    {
      "Name": "laxo",
      "Steam": "76561199631116344",
      "Score": 0,
      "Time": "??:??"
    },
    {
      "Name": "radianc3.lua owned u.",
      "Steam": "76561198799546256",
      "Score": 0,
      "Time": "??:??"
    },
    {
      "Name": "413",
      "Steam": "76561199131900979",
      "Score": 102,
      "Time": "??:??"
    },
    {
      "Name": "koifish.dragon571",
      "Steam": "76561199789320592",
      "Score": 52,
      "Time": "??:??"
    },
    {
      "Name": "forna",
      "Steam": "76561199079811625",
      "Score": 0,
      "Time": "??:??"
    },
    {
      "Name": "TigerIn",
      "Steam": "76561198729238712",
      "Score": 26,
      "Time": "??:??"
    },
    {
      "Name": "IHateAll.-",
      "Steam": "76561199813231700",
      "Score": 29,
      "Time": "??:??"
    },
    {
      "Name": "hydro x michael scofield",
      "Steam": "76561199103550667",
      "Score": 32,
      "Time": "??:??"
    },
    {
      "Name": "tymo",
      "Steam": "76561199425592793",
      "Score": 6,
      "Time": "02:21"
    },
    {
      "Name": "Prayer",
      "Steam": "76561199022017965",
      "Score": 99,
      "Time": "36:47"
    },
    {
      "Name": "cake",
      "Steam": "76561199387491541",
      "Score": 5,
      "Time": "04:38"
    },
    {
      "Name": "troubled",
      "Steam": "76561199629184110",
      "Score": 10,
      "Time": "93:48"
    },
    {
      "Name": "K3RMIT1337",
      "Steam": "76561199872685781",
      "Score": 0,
      "Time": "??:??"
    },
    {
      "Name": "AS1RIS",
      "Steam": "76561199094175893",
      "Score": 83,
      "Time": "36:52"
    },
    {
      "Name": "WoNg",
      "Steam": "76561198722930636",
      "Score": 36,
      "Time": "??:??"
    }
  ]
}