{
  "Time": "2026-04-10T09:10:25.5946957Z",
  "Players": [
    {
      "Name": "Unicorn",
      "Steam": "76561199109946506",
      "Score": 0,
      "Time": "??:??"
    },
    {
      "Name": "$$$$$$$$$$ | Drix",
      "Steam": "76561198726739170",
      "Score": 4,
      "Time": "??:??"
    },
    {
      "Name": "serzy_mecanic6",
      "Steam": "76561198733198194",
      "Score": 24,
      "Time": "??:??"
    },
    {
      "Name": "jaydens puppy <3",
      "Steam": "76561198780475574",
      "Score": 51,
      "Time": "??:??"
    },
    {
      "Name": "It's me",
      "Steam": "76561198717953119",
      "Score": 26,
      "Time": "??:??"
    },
    {
      "Name": "felix",
      "Steam": "76561198765165744",
      "Score": 0,
      "Time": "??:??"
    }
  ]
}