{
  "Time": "2026-04-28T02:16:54.3772554Z",
  "Players": [
    {
      "Name": "ен1гма топ адин",
      "Steam": "76561198720359951",
      "Score": 0,
      "Time": "??:??"
    },
    {
      "Name": "sazlamic4f",
      "Steam": "76561198723046699",
      "Score": 6,
      "Time": "07:23"
    },
    {
      "Name": "thatguy",
      "Steam": "76561198335255015",
      "Score": 107,
      "Time": "122:24"
    },
    {
      "Name": "48",
      "Steam": "76561198742407377",
      "Score": 30,
      "Time": "197:37"
    },
    {
      "Name": "DRAVEX",
      "Steam": "76561199798424764",
      "Score": 41,
      "Time": "64:21"
    },
    {
      "Name": "ebetti1805",
      "Steam": "76561199390203782",
      "Score": 53,
      "Time": "500:23"
    },
    {
      "Name": "lean",
      "Steam": "76561198728840802",
      "Score": 0,
      "Time": "02:48"
    },
    {
      "Name": "✪ Star /eversio",
      "Steam": "76561198720921416",
      "Score": 5,
      "Time": "??:??"
    },
    {
      "Name": "FractaL",
      "Steam": "76561198713353324",
      "Score": 14,
      "Time": "566:17"
    },
    {
      "Name": "Julian Qzeng",
      "Steam": "76561199699023502",
      "Score": 76,
      "Time": "117:12"
    }
  ]
}