{
  "Time": "2026-05-12T23:51:08.8838104Z",
  "Players": [
    {
      "Name": "\"'",
      "Steam": "76561199028888055",
      "Score": 0,
      "Time": "??:??"
    },
    {
      "Name": "LustHVH",
      "Steam": "76561199049938602",
      "Score": 88,
      "Time": "??:??"
    },
    {
      "Name": "mega",
      "Steam": "76561199686882374",
      "Score": 49,
      "Time": "16:30"
    },
    {
      "Name": "captain VAC sparrow",
      "Steam": "76561199847392950",
      "Score": 2,
      "Time": "547:54"
    },
    {
      "Name": "testing temple crack",
      "Steam": "76561199889944730",
      "Score": 5,
      "Time": "??:??"
    },
    {
      "Name": "gaminggenius2012",
      "Steam": "76561198170202181",
      "Score": 18,
      "Time": "??:??"
    },
    {
      "Name": "TempleWar | claudra",
      "Steam": "76561199062402973",
      "Score": 2,
      "Time": "??:??"
    }
  ]
}