{
  "Time": "2026-03-27T23:20:35.2060632Z",
  "Players": [
    {
      "Name": "Nim",
      "Steam": "76561199647822907",
      "Score": 0,
      "Time": "??:??"
    },
    {
      "Name": "Trionxs",
      "Steam": "76561199040781865",
      "Score": 29,
      "Time": "442:43"
    },
    {
      "Name": "ＳｈｅｇａＬ",
      "Steam": "76561198788812471",
      "Score": 0,
      "Time": "632:46"
    },
    {
      "Name": "Waze",
      "Steam": "76561198218118791",
      "Score": 22,
      "Time": "123:48"
    },
    {
      "Name": "Grizly",
      "Steam": "76561198188465877",
      "Score": 3,
      "Time": "??:??"
    },
    {
      "Name": "KKKasti",
      "Steam": "76561199833286399",
      "Score": 16,
      "Time": "12:18"
    },
    {
      "Name": "Jonny 88",
      "Steam": "76561198753890382",
      "Score": 41,
      "Time": "27:27"
    },
    {
      "Name": "angel",
      "Steam": "76561199761525290",
      "Score": 36,
      "Time": "??:??"
    },
    {
      "Name": "kittle ♡",
      "Steam": "76561199849665654",
      "Score": 23,
      "Time": "00:12"
    },
    {
      "Name": "z1R0",
      "Steam": "76561199874363237",
      "Score": 0,
      "Time": "12:43"
    },
    {
      "Name": "Lagrassa28AKA/DEALER",
      "Steam": "76561198743223911",
      "Score": 0,
      "Time": "412:30"
    }
  ]
}