{
  "Time": "2026-04-02T02:23:49.7321481Z",
  "Players": [
    {
      "Name": "\"'",
      "Steam": "76561199028888055",
      "Score": 0,
      "Time": "417:31"
    },
    {
      "Name": "nessie",
      "Steam": "76561199498486356",
      "Score": 0,
      "Time": "??:??"
    },
    {
      "Name": "keer",
      "Steam": "76561199860787478",
      "Score": 0,
      "Time": "??:??"
    },
    {
      "Name": "wong",
      "Steam": "76561198722930636",
      "Score": 0,
      "Time": "412:11"
    },
    {
      "Name": "Holocaust denier",
      "Steam": "76561199772489774",
      "Score": 2,
      "Time": "??:??"
    },
    {
      "Name": "nach Buidhe Dhu",
      "Steam": "76561198721107847",
      "Score": 0,
      "Time": "??:??"
    },
    {
      "Name": "Baracuda",
      "Steam": "76561199160093857",
      "Score": 2,
      "Time": "??:??"
    },
    {
      "Name": "Bwah",
      "Steam": "76561199381909573",
      "Score": 3,
      "Time": "32:11"
    }
  ]
}