{
  "Time": "2026-03-25T21:40:39.4947462Z",
  "Players": [
    {
      "Name": "\"'",
      "Steam": "76561199028888055",
      "Score": 0,
      "Time": "??:??"
    },
    {
      "Name": "CallMeSpoofer",
      "Steam": "76561199026396251",
      "Score": 2,
      "Time": "536:48"
    },
    {
      "Name": "пинокио из трущоб",
      "Steam": "76561199835990893",
      "Score": 3,
      "Time": "447:18"
    },
    {
      "Name": "yurilover9",
      "Steam": "76561198764733323",
      "Score": 23,
      "Time": "390:57"
    },
    {
      "Name": "Fresholdi",
      "Steam": "76561199492563531",
      "Score": 82,
      "Time": "05:32"
    },
    {
      "Name": "Benito Mussolini",
      "Steam": "76561198768490344",
      "Score": 49,
      "Time": "??:??"
    }
  ]
}